LICENSE
MANIFEST.in
README.md
setup.cfg
setup.py
py_factorio_blueprints/__init__.py
py_factorio_blueprints/blueprint.py
py_factorio_blueprints/book.py
py_factorio_blueprints/defaultentities.py
py_factorio_blueprints/entity.py
py_factorio_blueprints/entity_data.json
py_factorio_blueprints/entity_mixins.py
py_factorio_blueprints/entity_prototypes.py
py_factorio_blueprints/exceptions.py
py_factorio_blueprints/util.py
py_factorio_blueprints.egg-info/PKG-INFO
py_factorio_blueprints.egg-info/SOURCES.txt
py_factorio_blueprints.egg-info/dependency_links.txt
py_factorio_blueprints.egg-info/not-zip-safe
py_factorio_blueprints.egg-info/top_level.txt